{
  "projectId": "ef860978-8244-48b2-a8fa-4f953f2c2d0d",
  "generatedAt": "2026-03-04T18:05:39.708Z",
  "sections": [
    {
      "id": "btn",
      "label": "Btn",
      "file": "C:\\Users\\dean.guedo\\Documents\\GitHub\\canvas helper\\projects\\calm-module-2-activites-reference\\workspace\\components\\Btn.jsx",
      "sourceKind": "heuristic",
      "editable": true
    },
    {
      "id": "card",
      "label": "Card",
      "file": "C:\\Users\\dean.guedo\\Documents\\GitHub\\canvas helper\\projects\\calm-module-2-activites-reference\\workspace\\components\\Card.jsx",
      "sourceKind": "heuristic",
      "editable": true
    },
    {
      "id": "input",
      "label": "Input",
      "file": "C:\\Users\\dean.guedo\\Documents\\GitHub\\canvas helper\\projects\\calm-module-2-activites-reference\\workspace\\components\\Input.jsx",
      "sourceKind": "heuristic",
      "editable": true
    },
    {
      "id": "textareareflect",
      "label": "Text Area Reflect",
      "file": "C:\\Users\\dean.guedo\\Documents\\GitHub\\canvas helper\\projects\\calm-module-2-activites-reference\\workspace\\components\\TextAreaReflect.jsx",
      "sourceKind": "heuristic",
      "editable": true
    }
  ]
}
