{
  "projectId": "92b81c7c-1321-40e0-9b0a-a69b09442d64",
  "referenceId": "d2lccexport-129076-23-24-forensic-studies-25-per-1-a-b-sec-s3-202631302-2-ontent-i828b93d1-ea6b-427c-bde2-90c72532124b-content-section-2945-html",
  "generatedAt": "2026-03-14T13:27:13.170Z",
  "chunks": [
    {
      "id": "in-this-module-you-will-learn-about-the-breathalyzer-1",
      "index": 1,
      "locator": {
        "kind": "section",
        "label": "In this module you will learn about: the Breathalyzer",
        "sectionHeading": "In this module you will learn about: the Breathalyzer"
      },
      "text": "In this module you will learn about:\nalcohol and its effects upon the human body\nthe Breathalyzer\nthe Intoxilyxer and consequences of impaired driving\ncrime case studies involving impaired driving\nThis module has 2 assignments (content, case study) and 1 quiz.",
      "titleGuess": "In this module you will learn about: the Breathalyzer",
      "keywordHints": [
        "case",
        "driving",
        "impaired",
        "module",
        "alcohol",
        "body",
        "breathalyzer",
        "consequences"
      ]
    }
  ]
}
